openukge/__init__.py
openukge/data/__init__.py
openukge/data/dataset.py
openukge/data/load_data.py
openukge/data/ukg_data_module.py
openukge/data/ukg_sampler.py
openukge/data/word_vec_data.py
openukge/data/datasets/__init__.py
openukge/data/datasets/cn15k.py
openukge/data/datasets/mini-demo.py
openukge/data/datasets/nl27k.py
openukge/data/datasets/ppi5k.py
openukge/evaluation/ECE.py
openukge/evaluation/__init__.py
openukge/evaluation/confidence_prediction.py
openukge/evaluation/link_predict.py
openukge/evaluation/mean_ndcg.py
openukge/loss/__init__.py
openukge/loss/beurre_loss.py
openukge/loss/focuse_loss.py
openukge/loss/gmuc_loss.py
openukge/loss/gtranse_loss.py
openukge/loss/passleaf_loss.py
openukge/loss/ukge_loss.py
openukge/loss/ukge_psl_loss.py
openukge/loss/ukgse_loss.py
openukge/loss/upgat_loss.py
openukge/models/__init__.py
openukge/models/few_shot_model/__init__.py
openukge/models/few_shot_model/gmuc.py
openukge/models/ukg_model/__init__.py
openukge/models/ukg_model/beurre.py
openukge/models/ukg_model/focuse.py
openukge/models/ukg_model/gtranse.py
openukge/models/ukg_model/passleaf.py
openukge/models/ukg_model/ukge.py
openukge/models/ukg_model/ukge_psl.py
openukge/models/ukg_model/ukgse.py
openukge/models/ukg_model/upgat.py
openukge/models/word2vec/__init__.py
openukge/models/word2vec/cbow.py
openukge/models/word2vec/skipgram.py
openukge/training/__init__.py
openukge/training/beurre_trainer.py
openukge/training/focuse_trainer.py
openukge/training/gmuc_trainer.py
openukge/training/gtranse_trainer.py
openukge/training/passleaf_trainer.py
openukge/training/ukge_psl_trainer.py
openukge/training/ukge_trainer.py
openukge/training/ukgse_trainer.py
openukge/training/upgat_trainer.py
openukge/training/word_vec_trainer.py
openukge/training/training_utils/__init__.py
openukge/training/training_utils/early_stop.py
openukge/training/training_utils/optim_builder.py
openukge/utils/__init__.py
openukge/utils/device.py
openukge/utils/download.py
openukge/utils/seed.py
openukge-1.0.1.dist-info/licenses/LICENSE
openukge-1.0.1.dist-info/METADATA
openukge-1.0.1.dist-info/WHEEL
openukge-1.0.1.dist-info/top_level.txt
openukge-1.0.1.dist-info/RECORD
