Metadata-Version: 2.4
Name: OpenUKGE
Version: 1.0.1
Summary: OpenUKGE: An open-source Python library for uncertain knowledge graph embedding
Home-page: https://github.com/Chienking1997/OpenUKGE
Author: LiJianjing
License: GPL-3.0-or-later
Project-URL: Homepage, https://github.com/Chienking1997/OpenUKGE
Project-URL: Source, https://github.com/Chienking1997/OpenUKGE
Keywords: python-library,knowledge-graph,uncertain,embedding
Classifier: License :: OSI Approved :: GNU General Public License v3 (GPLv3)
Classifier: Programming Language :: Python :: 3
Classifier: Programming Language :: Python :: 3 :: Only
Classifier: Operating System :: OS Independent
Requires-Python: <4.0,>=3.8
License-File: LICENSE
Requires-Dist: requests>=2.31.0
Requires-Dist: tqdm>=4.66.1
Requires-Dist: numpy<2
Provides-Extra: dev
Requires-Dist: pytest>=7.0; extra == "dev"
Requires-Dist: flake8; extra == "dev"
Dynamic: license-file
